marvelous/FunctionalProcessing.py
marvelous/__init__.py
marvelous/collectionutils.py
marvelous/pipe/__init__.py
marvelous/pipe/registry/PipelineRegistry.py
marvelous/pipe/registry/PipelineRegistryEntry.py
marvelous/pipe/registry/__init__.py
marvelous/pipe/switch/SwitchBlock.py
marvelous/pipe/switch/SwitchBlockRegistryEntry.py
marvelous/pipe/switch/__init__.py
marvelous/util/__init__.py
marvelous/util/iteration.py
marvelous/util/typeutils.py
marvelouspy-0.0.0.3.dist-info/LICENSE
marvelouspy-0.0.0.3.dist-info/METADATA
marvelouspy-0.0.0.3.dist-info/WHEEL
marvelouspy-0.0.0.3.dist-info/entry_points.txt
marvelouspy-0.0.0.3.dist-info/RECORD
