Metadata-Version: 2.1
Name: MarvelousPy
Version: 0.0.0.3
Summary: Amazing functional programming interface for Python.
Home-page: https://github.com/dg-developer/MarvelousPy
License: Apache-2.0
Keywords: amazing,marvelous,functional,functional programming,fp,utility
Author: David Gayman
Author-email: drg.developer.2@gmail.com
Requires-Python: >=3.9,<4.0
Classifier: License :: OSI Approved :: Apache Software License
Classifier: Programming Language :: Python :: 3
Classifier: Programming Language :: Python :: 3.9
Classifier: Programming Language :: Python :: 3.10
Classifier: Programming Language :: Python :: 3.11
Classifier: Topic :: Software Development :: Libraries
Classifier: Topic :: Utilities
Project-URL: Documentation, https://github.com/dg-developer/MarvelousPy
Project-URL: Repository, https://github.com/dg-developer/MarvelousPy
